sioba_nicegui/__init__.py
sioba_nicegui/lib/xterm.js/xterm.js
sioba_nicegui/utils.py
sioba_nicegui/xterm/__init__.py
sioba_nicegui/xterm/base.py
sioba_nicegui/xterm/interface.py
sioba_nicegui/xterm/xterm.js
sioba_nicegui-0.1.20250906.3.dist-info/WHEEL
sioba_nicegui-0.1.20250906.3.dist-info/METADATA
sioba_nicegui-0.1.20250906.3.dist-info/RECORD
