Metadata-Version: 2.3
Name: sioba-nicegui
Version: 0.1.20250906.3
Summary: XTerm.js bindings for NiceGUI and sioba
Author: Aki Mimoto
Author-email: Aki Mimoto <aki@bako.ca>
License: MIT License
Classifier: License :: OSI Approved :: MIT License
Requires-Dist: nicegui>=2.23.0
Requires-Dist: sioba>=0.4
Requires-Python: >=3.10
